ses_device_driver/__init__.py
ses_device_driver/filesystem/__init__.py
ses_device_driver/filesystem/settings_file.py
ses_device_driver/ur10/UR_dashboard_client.py
ses_device_driver/ur10/__init__.py
ses_device_driver-0.2.2.dist-info/WHEEL
ses_device_driver-0.2.2.dist-info/METADATA
ses_device_driver-0.2.2.dist-info/RECORD
