Metadata-Version: 2.1
Name: ses-device-driver
Version: 0.2.2
Summary: Device drivers/helper classes for each device in the ses of Werk150
Author: Vinu ESB
Author-email: vinu.vijayakumaran_nair@reutlingen-university.de
Requires-Python: >=3.7,<4.0
Classifier: Programming Language :: Python :: 3
Classifier: Programming Language :: Python :: 3.7
Classifier: Programming Language :: Python :: 3.8
Requires-Dist: pyyaml (>=5.3,<6.0)
